agatereports/__init__.py
agatereports/basic_report.py
agatereports/adapters/CSVAdapter.py
agatereports/adapters/MysqlAdapter.py
agatereports/adapters/PostgresqlAdapter.py
agatereports/adapters/__init__.py
agatereports/engine/__init__.py
agatereports/engine/commonutilities.py
agatereports/engine/constants.py
agatereports/engine/jrxml2json.py
agatereports/engine/reportGenerator.py
agatereports/engine/bands/__init__.py
agatereports/engine/bands/bands.py
agatereports/engine/bands/elements.py
agatereports/engine/components/__init__.py
agatereports/engine/components/barcode.py
agatereports/engine/components/components.py
agatereports/engine/components/image.py
agatereports/engine/components/line.py
agatereports/engine/components/shapes.py
agatereports/engine/components/text.py
agatereports/exports/__init__.py
agatereports/exports/pdf.py
agatereports/java/__init__.py
agatereports/java/java_formatter.py
demos/__init__.py
demos/barcode.py
demos/blank_when_null.py
demos/datasource_csv.py
demos/datasource_mysql.py
demos/datasource_postgresql.py
demos/dates.py
demos/fonts.py
demos/hello_world.py
demos/image.py
demos/no_datasource.py
demos/number_formatting_sample.py
demos/page_format_A3.py
demos/page_format_free_page_size.py
demos/page_format_landscape.py
demos/page_format_margin.py
demos/run_all_samples.py
demos/shapes.py
demos/shapes_extra.py
demos/text_styles.py
demos/variables_system.py
demos/when_no_data_all_sections_no_details.py
demos/when_no_data_blank_page.py
demos/when_no_data_no_data_section.py
demos/when_no_data_no_pages.py
demos/when_no_data_null.py
agatereports-0.0.1.dist-info/LICENSE
agatereports-0.0.1.dist-info/METADATA
agatereports-0.0.1.dist-info/WHEEL
agatereports-0.0.1.dist-info/top_level.txt
agatereports-0.0.1.dist-info/RECORD
