Metadata-Version: 2.1
Name: agatereports
Version: 0.0.1
Summary: python report generator engine to process JasperReports jrxml file.
Home-page: https://github.com/ozawa-hi/agatereports
Author: Hitoshi Ozawa
Author-email: ozawa_h@gmail.com
License: BSD license (see LICENSE for details), Copyright (c) 2019, Hitoshi Ozawa
Platform: UNKNOWN
Classifier: Development Status :: 3 - Alpha
Classifier: Intended Audience :: Developers
Classifier: License :: OSI Approved :: BSD License
Classifier: Topic :: Office/Business
Classifier: Topic :: Printing
Classifier: Topic :: Software Development :: Libraries :: Python Modules
Classifier: Topic :: Text Processing :: Markup
Classifier: Topic :: Utilities
Classifier: Programming Language :: Python :: 3.6
Requires-Dist: reportlab (>=3.4.0)
Requires-Dist: mysql-connector-python (>=8.0)
Requires-Dist: psycopg2-binary (<2.8,>=2.7)
